<protokoll>
<head>
<vald>keskmurre</vald>
<aeg>xx.xx.1867</aeg>
</head>
<sisu>
Wilja seaduse pärrast arro piddaminne , ülles wõetud 2sel Octobri ku päewal 1867. 
Tallitaja , kohtomehhed ja Wolli meehhed kui ka keik Walla perre meehhed , olled kokko tulles ülles arwanud : et nemmad oma tännawusse Wiljaga kunni tullewa leikuseni läbbi sawad - et ostmist tarwis ei olle . 
Magasini Aidas on 93 Tsehtwerki , 2 Tsetwerikut Rukkid , mis weel wõlga on soab keik sisse maksetud , nenda samma ka sui willi , mis sesse on tullemas . 

</sisu>
</protokoll>
