<protokoll>
<head>
<vald>keskmurre</vald>
<aeg>xx.xx.1868</aeg>
</head>
<sisu>
Serrewerre mõisas sel 28mal Junil 1868 koos ollid kohtomehhed Adam Rosenstrauch Hans Pent Jaan Holtblom Ette tulli kaebaja Karel Preimann rukkiste pärtrast mis ollid weski jurest ärra witud , ja temma wastane , Ado Emann ja möldre pois Ado Widikas . 
Ado Widiks ütleb , et temma ei olle mitte sedda rukki kotti Ado Emannil annud . 
Ado Emann ütleb , et poisid Ado ja Hans on temmal selle kotti annud . 
Ado Emann ütleb et temma kot on ärra witud weske jurest ja sellepärrast temma wõera wõtnud . 
Leppisid ärra ja maksid Ado Widik ja Ado Emann mõllemad pool rubbala Karel Preimannil . 
Serrefer : d 23 Juni Kohto wannem Adam Rossenstrouh / allkiri / abbimees Hans Pent XXX abbimees Jaan Holtblom XXX 

</sisu>
</protokoll>
