<protokoll>
<head>
<vald>keskmurre</vald>
<aeg>xx.xx.1876</aeg>
</head>
<sisu>
Kaebas Loho moisa metsawaht Jaan Klem , et walla rahwa sead on wastu keeldu moisa metsas palju maad üles tustinud : Sead olid : Urgel 5. 
Siga Kangrul 2. 
Siga Araka sauna 1. 
Siga . 
Said need kolm sigade peremeest ette kutsutud ja küsitud kas tõsi on : need Otto Neufeldt ja Daniel Wunder ja Mart Jakobus tunnistasid , isi seda tõsi olewad . 
Ja Otto Neufeldt tunnistas et ka Kassil on 4. siga ja Kadakal on 3. siga mis ka keik se sui on seal tustimas käinud , ja Daniel Wunder ja Mart Jakobus tunnistasid seda tõsi olewad . 
Kogukonna kohus moistis , et iga sea pealt peab üks Rbl . 
moisa trahwi maksma . 
15. siga ja 15. 
Rbl . 
( Otto Neufeldt ja Daniel Wunder ja Mart Jakobus maksis omad trahwid sel samal pääwal wälja . ) 

</sisu>
</protokoll>
