<protokoll>
<head>
<vald>keskmurre</vald>
<aeg>xx.xx.1874</aeg>
</head>
<sisu>
Puurmannis sel 18 Marzil 1874. 
Koos ollid Peakohtumees Hans Perre kohtumees Tõnno Bauer " Jürri Luhha Trino Kawe tulli tännasel päiwal sija kohtu ette , ja andis ülles , et temma tahtma töistkorda abbiellosse minna ja mis see järrel jänud wannast abbiellost warrantus on koggukonna kohhus ja temma wöölmöldrid järrel wadanud mis siin all nimmetud on , jääb temma poja Märt Kawe ja temma ommaga kokko , ja see on keik selle warrandus , mis seal majas on , ja saab perrast siis jaotud kui poeg täie ealiseks saab , ja perrast peab temma omma issa öigusses sama , et temma see Märt Kawe maja kontraht saab . 
1. 
6 Lehma a 15 Rbl . 
tuk 90 Rbl höb . 
2. 
3 öhwa kokko 20 " " 
3. 
2 wassikad kokko 3 " " 
4. 
8 Lammast a. 2 Rubl . 
tük 16 " " 
5. 
7 Talle a. tük 50 cup . 
3 " 50 
6. 
4 Sigga kokko 24 " " 
7. 
3 hobbust kokko 110 " " 
8. 
4 kanna 1 " " 
9 " hobbuse riistad 2 " 50 
10 3 Regge kokko 3 " " 
11 2 wangert kokko 10 " " 
12 2 addra kokko 2 " " 
13 1 saksama adra 12 " " 
14 1 Linna massin 2 " " 
15. 
5 Sirpu kokko 
50 cop 
16. 
5 wikkatid kokko 1 Rbl 50 cop . 
17. 
2 törd kokko 2 " 50 kop . 
18. 
1 wilja wak 1 " " 
19. 
3 kirstu ja üks kast , kokko 5 " " 
20. 
Kirwed kokko 1 " 30 k 
21. 
3 hoowlid kokko 1 " 50 k 
22. ohherd ja kowwer kirwes , kokko " " 50 
23. wilja keik kokko 126. 
" 75 
24 12 wilja kotti kokko 4 " 80 
25 üks kassuk 7 " " 
26 2 kampsoni kokko 5 " " 
27. 
1 suwwi mütz 1 " " 
28. 
1 kuwwe täis ried 5 " " 
29. 
3 padda kokko 3 " 20 
30. kangastelled 1 " 50 
31. 
2 lauda kokko 2 " 35 
32. 
2 wokki kokko 1 " 40 
33. 
4 kanga sugga kokko 2 " " 
34. üks kässi kiwwi 1 " " 
35 1 raud kang 1 " " 
36. sönniku angud ja raud labbidas 1 " " 
37. üks saak " " 25 k 
38. 
12 liuda a 6 kop tük " " 75 
39. 
10 piima pütti kokko 1 " " 
40. 
2 weepangi " 
20 
Summa keik kokko 485 Rbl . 
puhhast rahha on 30 " . 
Summa 515 Rbl . 

</sisu>
</protokoll>
