<protokoll>
<head>
<vald>keskmurre</vald>
<aeg>xx.xx.1884</aeg>
</head>
<sisu>
Protokolli põhjusel 24 Maist s . 
a. N : 104 astus kohtu ette Suurest-Kõppust Ado Pollmann ja tunnistas et Willem Oja ise temale ütelnud et temal kuude peale Jaan Naariga kaup olnud . 
Kaebaja kui kaebataw said kohtu ette nõutud ja neile tunnistuste wälja ütelused ette loetud kui kohtu poolt omawahel ära leppimist pakutud mis aga kokku ei läinud . 
Willem Oja ütles et tema 28 päewa teinud 45 kop . 
päew . 
Otsus : Jaan Naaris oma tunnistuse järgi et Willem Oja teda üks kuu 11 rubla eest teeninud , maksab selle teenitud palga wälja , säält lähab aga Willem Oja kahjus tunnistuse põhjusel et kuu peal kaup olnud ja kauba murdnud 3 rubla maha seejärgi maksab Jaan Naaris Willem Ojal 8 päewa aea sees 8 rubla hõb . 
tööpalgaks wälja . 
See otsus sai kohtu käijatel kohe kuulutatud . 
Pääkohtumees : Andres Ekbaum [ allkiri ] Kohtumees : Peet Amann [ allkiri ] Kohtumees : Peter Bergmann [ allikiri ] Kirjutaja : [ allkiri ] 

</sisu>
</protokoll>
