<protokoll>
<head>
<vald>keskmurre</vald>
<aeg>xx.xx.1869</aeg>
</head>
<sisu>
Moisa Herra kaebab et Karel Promet on Öhsi toa Tüttruko Jula Mei jures keinud ja moisa aknat ärra löhkonud . 
Tütruk Jula tunnistab et Karel Promet olla ommiko kello 3 ajal toas keinud küssinud miss Kella aeg olla , Koja uks on sis wel kinni olnud kust Promet sisse tulnud setta temma ei tea . 
Karel Promet tunnistab et temma mitte sellest Aknast ei olle sisse tulnud kust Rudut ärra löhadut ta on Palkonni alt ühhest teisest aknast sisse leinud . 
Moisteto . 
Tütruk Jula Mei peab 2 Rubla walla Laeka trahwi maksma et mitte koche ei olle tunnistanud kess temma jures on keinud ja Karel Promet 4 Rublaga walla Laeka et temma aknadest sisse leheb Öh ajal kuss temmal lubba ei olle päwa ajal keija . 

</sisu>
</protokoll>
