<protokoll>
<head>
<vald>keskmurre</vald>
<aeg>xx.xx.1880</aeg>
</head>
<sisu>
Leno Ummus kaebab : Temma kirstust on pois Jürri Arrosoo 3rubla 85kop . 
rahha ärra warrastanud , 3rubla 40kop . 
on jo kätte saanud , seda on sellest weel 45kop . 
ja enne on weel temma kirstust se pois rahha wõtnud . 
Pois Jürri Arrosoo tunnistab : Temma on nüüd selle rahha wõtnud ja 3rubla ja 40kop . 
ja kätte annud ja enne on wõtnud ükskord 60kop . 
teine kord 95kop . 
Se on üllepea 2rubla mis weel poisi käes on . 
Kohus mõistis : Jürri Arrosoo peab selle rahha 2rubla taggasi maksma ja saab 20 hopi witso trahwi . 
Kohto wannem : Juhhan Suursild Kohto käemehhed . 
Juhhan Kant , Hans Härg Kirjotaja H.Siimson 

</sisu>
</protokoll>
