<protokoll>
<head>
<vald>keskmurre</vald>
<aeg>xx.xx.1888</aeg>
</head>
<sisu>
Protokoll № 1 Sel 25. 
Januaril 1888. 
Koku ollid tulnud kohtu peawannem : Peeter Somberg Kõrwamees : Mart Limberg ja Jakup Weber . 
IV . 
Wanna tallitaja Juhan Priima kaebas , et Tõnnis Hermann ei olle oma kohtu trahwi 1 Rb 50 kop . 
mis Protucoll N 12 sel 2. 
Nowembr . 
1887 mõistetud sai , mitte ärra maksnud ja ei lubagi mitte maksta . 
Tõnnis Hermann tulli ette ja ütles , et temma sedda kohtu otsust ei täida ! 
Kohus mõistis , et Tõnnis Herrmann peab seda trahwi 1 Rb 50 kop . 
mis kohtu poolt mõistetud , 8 pääwa aea sees ärra täitma ja kui mitte , siis saab tallitaja poolt se wõis [ ? 
] riisutud . 
Kuulutud ! 
täidetud 
Kohtupea wannem : Peeter Somberg XXX Kõrwamees : M. Limberg XXX ja J. Weber XXX Kirjutaja : T. Nacks / allkiri / 

</sisu>
</protokoll>
