<protokoll>
<head>
<vald>keskmurre</vald>
<aeg>xx.xx.1897</aeg>
</head>
<sisu>
1897 aastal 28 Webruari k . 
p . 
ilmusid Wäetsa walla kohtusse Kirna walla liige Jaan Hansu p . 
Kruusman ja Wahastu walla liige Mart Jaani p . 
Künstler , kohtule mõlemad iselikult tuntud , ja palusid kohtu aktiraamatusse üleswõtta endi suusõnalist mahategu , mis järgmine on : Mart Künstler müib oma rendikoha pidamise eesõiguse , mis Wäetsa wallas " Sepa " koha nime all ja Ann Mikowi päralt on Jaan Kruusmannile selle tingimisega , et ta täidab nimetud koha kohta need tingimised , mis Wäetsa walla kohtu akti raamatus üles on tähendud 1895 a. 26 Mai kp . 
N 10 all s.o. need samad tingimised , millega Mart Künstler selle koha Ann Mikowi käest on rentinud . 
See mahategemine hakkab maksma 23 Aprilli kp . 
1897 a. Käesolew Mahategemine sai pärast aktiraamatusse kirjutamist pooltele etteloetud ja nende polt alla kirjutud . 
Jaan Kruusmann ei oska kirjutada , tema palwe peale kirjutas tema eest alla J. Leht / allkiri / M. Küntsler / allkiri / 
Kohtu Eesistuja A. Ehrenwert / allkiri / Kohtumehed A. Nipper / allkiri / M. Prant / allkiri / Kirjutaja K. Pommer 

</sisu>
</protokoll>
