<protokoll>
<head>
<vald>keskmurre</vald>
<aeg>xx.xx.1876</aeg>
</head>
<sisu>
Koos ollid : Kohto wannem Pridik Woldrat Kohto käemees Juhan Lehtmets ja Härmo Liwak . 
Tallitaia ja Hans Otsman andsid ülles et nemad on teind seda kaupa , et Hans Otsman pühib koli toa ja kohto toa korstnad , ja parandab ahjud kui neil weikest wiga juhtub , saab selle ette ühe aasta pealt 3 rubla 60 kop . 
1877 aasta esimisel Januari ku kohto päwal saab kätte makstud . 
Kohto wanem Pridik Woldrat Kohto käemees Härmo Liwak Kohto käemees Kirjutaia M. Lewet . 
Kose kih . 
k . 
poolt sel 20 Detstril 1876 läbiwaatatud . 
/ allkiri / , kohtuwanem . 

</sisu>
</protokoll>
