<protokoll>
<head>
<vald>keskmurre</vald>
<aeg>xx.xx.1867</aeg>
</head>
<sisu>
1 ) Ette tulli Marri Midri ja kaebas : temma perremees Jürri Reinberg on tedda lahti lasknud omma tenistussest ja temma ei woi wasto talwe nüid kostkilt tenistust sada sest et leib kallis on ja pealegi ollen aasta peale kauplenud . 
2 ) Jürri watab : temma ei woi mitte Marrid piddada , sepärrast et temmal warguse ammet wägga tuttav on . 
Sest minnul on mitmed asjad maiast ärra kaddunud , ei ma teadnud enne kui nüid tedda korrale tulatud odra hunniku kallalt leitsin et temma se warras on ja selle peale lasksin tedda lahti . 
3. 
Marri tunnistab et temma on sullase kässo peale hobbusele tahtnud need odrad wia . 
4 ) Sullane wastab et temma ei olle kaskinud wõtta . 
5 ) Tunnistab Marri et temma on warrastanud . 
6 ) Koggokonna kohhus moistis : Marri seisab 24 tundi puris se eest et ei pea warrastama . 
Agga peale sedda peab perremees tedda taggasi omma tenistusse wotma . 
Kui Marri peaks siis weel eddes piddi warrastama woib perremees tedda ärra aiada , ilma et Marril middagi õigust olleks 

</sisu>
</protokoll>
