<protokoll>
<head>
<vald>keskmurre</vald>
<aeg>xx.xx.1883</aeg>
</head>
<sisu>
Jaan Wäljaots tunnistas Märt Laarepera Kaebtuses 6 Oktobrist s . 
a. N ; 162 : Jaan Pillan olewat rääkinud , tema oleks Tõruma kõrtsis kaks püssi rauda osta saanud , pole aga raha olnud , Kõrtsimees pole ka annud , teine kukk olnud wasega joovetud ja õige linditega , kellel see püss müüja olnud pole Pillan ütelnud . 
Jaan Põdder ütles ennast sest asjast midagit teadwat . 
arwatud Jaan Pillan ja Peet Reinberg teiseks korraks wahi all ette tuua laske . 

</sisu>
</protokoll>
