<protokoll>
<head>
<vald>keskmurre</vald>
<aeg>xx.xx.1876</aeg>
</head>
<sisu>
Sel 12mal Julil 1876. 
Hindrek Laisk andis ülles et Abram Prosowits olla temma last ( Kustas Laiska ) kinni wötnud ja koeraga purretanud nenda et kaks werrist armi järrel ollid Kohhus möistis parragrahw 1232 järrel Abram Prosowitsale 10 witsa hopi ja poisid Kustas Laisk ja Jürri Lelleputi koera narrimisse eest kumbki 1 rubla walla laeka se on kaks rubla Kohtowannem Jaan Walge XXX ab . 
Sander Kotlipson XXX Juhanes Reinmann XXX 

</sisu>
</protokoll>
