<protokoll>
<head>
<vald>keskmurre</vald>
<aeg>xx.xx.1880</aeg>
</head>
<sisu>
Se asi sai ette wõetud , waata protokoll № 18 , 1880 ja protokoll Juhan Piiskoppi ja Kustas Mõistlikku kuuldes ette loetud . 
Kohus arwab Kustaw Mõistliku sü aluseks , sest et kohtumehed seda asja warsi ja igalt poolt nõnda on kuulnud rääkiwad , ja ka weel teisi tunnistusmehi kes seda löömist on näinud nõnda tõsi olewad , kuida Juhan Pütsep on tunnistanud . 
Kohus pakkus neile leppitust , Juhan Piiskop pärib aga lepimiseks Kustas Mõistliku käest 3 rubla käelööma hoobi eest , ja puuga hoopide ette jättab suurema kohtumõistmise alla . 
Kustas Mõistlik ei wõta seda kuulda waid tahab , et Juhan Piiskop peab teda paluma . 
Nemad ei ole lepinud , protokol wälja antud . 
Peakohtumees Aadu Sengbusch XXX Kõrwasmehed Rein Rick XXX Kustas Silbermann XXX Protokoll wälja antud Hakentrehi kohtule . 

</sisu>
</protokoll>
