<protokoll>
<head>
<vald>keskmurre</vald>
<aeg>xx.xx.1874</aeg>
</head>
<sisu>
Harmi . 
1 ) Kaebtuseks tulli ette Armi walla Metssawaht Jürri Kalus kaebas , et Armi walla Rentnig Kärt Unwits on omma Einnama pealt nelli Kasse puud raijund 9 1 / 2 Tolli jämedat , ilma möisa lubbada , ei ka metsa wahhile ei olle teada annud . 
2 ) Tulli ette Kärt Uwits ütles et temma omma Einnama puhastamise pärrast need kassed on ärra Raiund , need kased olnud kuiwi okse täis ja pilland neid allati Einna sisse mahha tüliks selle pärast on temma need kased ärra raijund 3 ) Kohtu möistus olli , et Keart Uwits omma einama puhastamese pärast need kolwatumad kased on raijund , on peremehe öigus omma Einamaad puhastada ei olnd temma suur süi allune leida , agga et temma ilmma kellegi lubata on sedda teind maksab Trahwiks walla Laega 1 Rub . 
ja pude est möissa 1 Rubla . 
Kohtupeawanem T. Tiedeperg Kohtukäemes J.Rosenpaum Kohtukäemes J. Kugel Kirjutaja M. Eichthal Mõistetud . 
Möistus täidetud . 
2. 
Rub . 
makstud . 

</sisu>
</protokoll>
