<protokoll>
<head>
<vald>keskmurre</vald>
<aeg>xx.xx.1885</aeg>
</head>
<sisu>
Karl Elijas tunnistab , ( waata protokoll № 11 - 1885. a. ) et tema Juhan Riineri rahast ei tea , ega ole näinud , kas Juhanil on raha olnud kautada wõi mitte . 
Tema toonud kül Juhan Riineri Lokota kõrtsist wälja , ja Juhan olnud wäga purjus , ja pilland kaks wiekopika tükki maha kõrtsi ette , ja tema wõtnud need üles , ja Juhan ise annud kolm wiekopiku tükkki weel tema kätte ja need jäänud teise homikuni tema kätte , ja Juhani mütsi wõtnud ka ära wiinud omale , selle mõttega , et pärast mõni wõtab ööse Juhani mütsi peast ära , ja jätnud Juhani enese Lokkota kõrtsi ette pitkali maha . 
Teisel homikul annud se 25 kop . 
ja mütsi Juhani kätte , ja siis Juhan kaeband , et temal raha kadund olla , aga ei ole üttelnd kui palju raha tal ära kadunud , jääb teiseks kohtu päewaks . 
Pea Kohtumees Hans Rick XXX Kõrwasmehed Märt Wärtmann XXX Mihkel Sengbusch XXX Kirjutaja K. Waarmann 

</sisu>
</protokoll>
