<protokoll>
<head>
<vald>rannamurre</vald>
<aeg>xx.xx.1877</aeg>
</head>
<sisu>
Andres Spriit sai ette kutsutud ja temalt küsitud : kuida sa Käsmu mehe lina leisika , kasuka ja m . 
t . 
kraamid Haljalas ree päält ära warastasid ? 
Andres Spriit wastas : mina ei ole neid mitte warastand ; mina leidsin , se lina leisikas oli Haljalas minu rees , kasukat ega muud kraami mina sääl ei näind . 
Ma küsisin : kelle see lina leisikas on minu rees , tulgu pärigu ära pärima ei ole keski tulnud . 
Jaagup Wasserman on ka seda kuulnud , kui tema on neid linu kääst ära pakund , se on wiimaks öölnud , ära pakku liiga , pärib mõni ära kelle oma ei olegi , wii edasi , kül se kätte saab kelle oma on , siis tema toonud koiu ja annud teadust igale poole . 
Kustaw Suksthw ütles : sina oled siis Haljalas olnud kui mina lina leisikat otsisin ( miks sa kätte ei annud ) seda tunistasid mulle Kustas Joosepson , Juhan Tomula ja Juhan Pluum . 
Tunismehi ei olnud wõimalik ette saada otsuse tegemine jääb järgmiseks kohtupääwaks . 
Jaagup Perkström XXX , Juhanes Uukareda XXX , Kustaw Rusalep XXX 

</sisu>
</protokoll>
