<protokoll>
<head>
<vald>läänemurre</vald>
<aeg>xx.xx.1893</aeg>
</head>
<sisu>
Üks tuhat üheksa sada üheksakümmend kolmandamal aastal 22 Talwe kuu pääwal ustawaks tunistud , et Piirsalust Weikse-Tiidu koha omanik Jaan Kruuspann on oma käega alla kirjutanud kohtu ees selle tunnistuse kirjale , et on 1889 aastal Karl Kreenile müünud elu maea palgid , segamine kuused ja männad , mille hind on kõik täieste makstud . 
Wanem : J Willenthal [ allkiri ] Liikmed : Joh Freibach [ allkiri ] " : K Allison [ allkiri ] " : Adam JIs [ allkiri ] Kirjutaja a. t . 
AHeide [ allkiri ] 

</sisu>
</protokoll>
