<protokoll>
<head>
<vald>läänemurre</vald>
<aeg>xx.xx.1908</aeg>
</head>
<sisu>
Üks tuhat üheksa sada kaheksamal aastal Märtsi kuu 10mal päewal Sooniste wallast elanikud Luiste walla liige Jaan Mihkle poeg Uuberg ja Kolowere walla liige Jüri Pillenberg Jaani poeg , kes kohtule isiklikult tuntud on , palusid selle kohtu lepingute raamatusse järgmist lepingu ülesse kirjutada : Jüri Pillenberg annab Jaan Uubergi kätte kuue aasta peale pruukimiseks : 
paar härgi hinna all 100 rbl . 
1 hobune " 50 " 
2 lehma " 60 " 
2 mulikast " 40 " 
3 siga " 24 " 
9 lammast " 27 " 
1 regi " 1 " 
1 raud assidega wanker " 10 " 
Kokku 312 Rbl 
Kui neid asju ehk loomi selle hinna wäärtuses Uubergil anda tagasi ei ole siis annab raha mmis ülewal tähentud Pillenbergile . 
See leping on pärast lepingute raamatusse kirjutamist pooltele ette loetud ja nendest õigeks tunnistud . 
Jaan Huberg [ allkiri ] Jüri Pillenbergi kirja oskamata oleku pärast tema palwe peale kirjutab alla E Kannuek [ allkiri ] Tunnistab õigeks Presidendi as . 
J. Habermann [ allkiri ] Liikmed : J. Jis [ allkiri ] " : P Onenar [ allkiri ] Kirjutaja as . 
A Heide [ allkiri ] 

</sisu>
</protokoll>
