<protokoll>
<head>
<vald>läänemurre</vald>
<aeg>xx.xx.1871</aeg>
</head>
<sisu>
Kohto korra pärrast ollid kokko tulnud . 
Kohtowannem : Hans Einbaum abbimees : Jakop Nomberg Hans Loopmann Kirjutaja C. Reinwalt Astus ette Rouma walla perremees Mäe Maddis Praun kaewab Rouma perremehhe Loigo Mart Loikowi peale , et Mart on temma karjast Karl Beertmanni vängaste peksnud , sellepärrast et karjane Mardi heinamas on olnud . 
Astus ette Mart Loikow , ja ütleb , et temma on läinud karjast heinamast wälja aiama , et ta niitmata heinamas on olnud , karjane hakkand wastu räkima , ja ei olle tahtnud ärra minna , siis olle Mart kolm korda ühhe weise witsaga karjast lonud , agga ennam ta ei olle waewa teinud . 
Moistatus : Et Mart kolm korda on karjast lönud , selle ette maksab ta poolteist rubla karjotsele loma ette ja poolteist rubla walla laekase trahwiks : rahha sai selsammal päwal makstud . 
abbimees : Jakop Nomberg XXX Hans Loopmann XXX 
Kirjutaja C. Reinwalt 

</sisu>
</protokoll>
