<protokoll>
<head>
<vald>läänemurre</vald>
<aeg>xx.xx.1887</aeg>
</head>
<sisu>
2 Astus ette moisa metsa waht Hans Mauer ja ütles Jaan Einsel , ja Jaan Walbet on moisa küni warrawa lahti murdnud , ja ühe kolme süllase laua katki raiunud . 
Astussid ette kaewatawd Jaan Einsel ja Jaan Walbet , Einsel ütles Walbet murdis küni warrawa laht , ja minna raiusin selle laua katki moisa vankre pohja lauda . 
Kohus moistis 1 , et kaewataw Jaan Einsel maksab 50 kop walla laeka 2 , Jaan Walbet saab 20 hopi witsa . 
Kohtowanem Jaan Karing ( allkiri ) Kohtokorwamehed Kustas Sewermann XXX Jaan Liiw XXX Kirjutaja Kustas Liiw 

</sisu>
</protokoll>
