<protokoll>
<head>
<vald>läänemurre</vald>
<aeg>xx.xx.1877</aeg>
</head>
<sisu>
39. 
Ano Prins Mihkli naine Elbust kaebas et temal üks oinik tal on kewade Karomatsi lammaste sekka läinud ja kui ta lamba niida aeal enne Jaani pääwa oma talle on kätte küssinud , ei ole Jakob Morits seda temale mitte kätte annud ja ütlenud et se tema oma lammas olla . 
Kaebaja nõuab seda lammast ehk 1 1 / 2 Rubla kätte . 
Jakob Morits ütles et tema lammaste seas mitte ei ole üht wõerast talle lnud ja olla temal kõik oma lambad . 
Et nad kummaltki poolt selle asja üle tunnistust ei saanud ja mõlemad seda talle omaks nimetawad , sai mõistetud Jakob Morits peab poolt hinda mis on 75 kp Ano Prints kätte wälja maksma ja jääb se tal temale . 
Sai makstud . 

</sisu>
</protokoll>
