<protokoll>
<head>
<vald>läänemurre</vald>
<aeg>xx.xx.1859</aeg>
</head>
<sisu>
Ette olli tulnud kaibaja Wendramees Hans Tommingas ja temma wastane Andres Tölp tülli pärrast Hans on Andrese käest Wesgel noa süija wõtnud sest etta ommal on koju unnetand Andres on noa temale süija annud ja läinud isse kõrtsi nugga jänud Hanso kätte , Hans sanud sönud siis läinud Andrest otsma agga ei olle mitte leidnud , pärrast Hans olnud Wesge kojas ajand jahho kotti , Andres tulnud sina ja küssind miksa minno nugga kätte ei annab Hans ütlend nugga on minno käe ma annan kätte Andres ütlend muido ma ei wõtta kui pool toopi wiina peab liggi ollema trahwi Hans ütlend kui teil se wõimus on siis ma pean andma egga ma sii teddega tülli ei woi tehha ja andnud pole tobi wiina rahha . 
Sedda tunnistas Tõnnis Kask et se keik tõssi on Andres ütles et se assi on nenda olnud agga tema ei olle isse sedda wiina jonud teised on ärra jonud sai mõistetud - . 
Et Andres maksab Hansole se wiina rahha taggasi ja saab selle rummala teo eest 10 hopi witso 

</sisu>
</protokoll>
