<protokoll>
<head>
<vald>läänemurre</vald>
<aeg>xx.xx.1888</aeg>
</head>
<sisu>
Anders Notmann astus kohtu ette , ja andis ülese . 
Et tema tahab wõtta Maria Rehe oma juure elama , ja lubab teda toita ja katta surmani . 
Aga Maria Rehe peab ka nenna palju tööd tegema kui palju tema terwis teda lubab . 
Ka ei tohi tema tüli perekondas teha , waid peab keiki perekonna liikmeid nenna armastama nagu omakseid , ja üks Lammas on temal ka luba pidada . 
Selle peale sai Marie Rehe ette kutsutud , ja Andres Notmanni ette panek ette loetud , mis peale tema oma rahulolemist tunnistas . 
Nenna nagu naad üksteisega lepisid , siis ei olnud walla Kohtul ka selle wasta ühtigi . 
Kohtuwanem A.Benholm + + + , Juuresistuja H.Alberg + + + , L.Alström + + + , A.Lindström + + + , J.Jäemees + + + 

</sisu>
</protokoll>
