<protokoll>
<head>
<vald>Võru murre</vald>
<aeg>xx.xx.1870</aeg>
</head>
<sisu>
Jakob Liiskmann wõttab Tosikatse ma Peter Luiskmanni käest , ni kui Peetre kontraht om tettu . 
Jakob lubbab keik ellajad , nink maia kraam mes issa kättte annab norema wellel Gustawel nink Janil sissaral Hellol hoita temma lubbab issal nink tema lastel üllespidamist anda omma lewwaga welled niong sõssart kaswata senni kui innimesses sawa . 
peter lubbab omma lapstega tallo tööd omma jau piddi tehha . 
Nenda herr lubbab sedda . 
Tosikatse kontrakti Jakobi kätte anda , nink Raigala maa Jakobi käest Jürripäewal 1870 wastu wõtta . 
Räppina koggokonna kohhus sel 24 Märzil 1870 Jakob Liiskmann XXX Peter Liiskmann XXX 

</sisu>
</protokoll>
