<protokoll>
<head>
<vald>Võru murre</vald>
<aeg>xx.xx.1867</aeg>
</head>
<sisu>
Kahkwa kog . 
kohtu een sel 5 Marzil 1867. 
Kaiwas Peep Obrand et temma welli Jaan temmale wõlgo om ja ärra ei massa . 
Temma om Jaanile 9 Rubla rahha hobbese osta lainanu ja üts küllimit linna seemnita ja üts zuwa nahk masnu 2 R 70 Kop ja kallu 60 Kop kartohwlit 180 Kop . 
Ette tulli Jaan Obrand ja ütel et tema Peepule 9 Rbl wõlgo ollu ja 6 R ärra masnu ja 3 R weel massa . 
Kohhus mõist et Peep om keigest maju häst jaggo saanu arwati sest , wõllast weel Jaanil Peepule massa 5 R 55 Kop rahha ja küllimit linna seemnit . 
Rein Oinberg Jakob Lepland Johhan Sepp 

</sisu>
</protokoll>
