<protokoll>
<head>
<vald>Võru murre</vald>
<aeg>xx.xx.1867</aeg>
</head>
<sisu>
Kahkwal sel 17 julil 1867 Kaiwas Mikka Hamkow , et Saara Waaks olles temma naist pesnu kui tedda koddo es olle . 
Iwwan Hamkow üttel , et tema olles appi saanu kui S. Waaks om temma sõssart pesnu ja om sõssara Saara käest ärra pästnu . 
Kaiwatawa Saara Waaks ütel , et Mikka Hamkowi naine om tedda kolme mehhe horas sõimanu , temma om Mikka naise käest küssima lännu kelle hor temma om , sis olles Mikka naine omma wellega tedda pesnuwa . 
Et õiget tunnistust es olle jäi se assi tõiste tunistajate ütlemise pääle . 

</sisu>
</protokoll>
