<protokoll>
<head>
<vald>Võru murre</vald>
<aeg>xx.xx.1875</aeg>
</head>
<sisu>
Sel sammal päiwal Fr Gross kaibusen wasta Liso Meus soimamise perrast temma emmandat . 
tunnistaja I Peter Tutt ütles wälja et soimamist ei olle minna kuulnu enge Liso Meus üttelnu Gross emmanda wasta , aja omma karri sist ärra omma maa päle . 
- Liso Meus ütles minna ütli emmandale kas se häbbi ei olle et minnu ärra ajat sist , minne parremb koddo ja kedda ommale karjasele parremb putro . 
II Tunnistaja Marri Märtimäggi ollew haige nink mitte tulnu . 
Peter Tutt ütles et kari sis olli to kõrd Grossi maa pääl Laukanidu pääl . 
tõises kohtu päiwas . 

</sisu>
</protokoll>
