<protokoll>
<head>
<vald>Võru murre</vald>
<aeg>xx.xx.1887</aeg>
</head>
<sisu>
Protokolli edesiminek N109 . 
Katre Mitt ( mansaisja Karel Lepland ) and wastust : mina wõtti küll Jaan Säkna mõematsest pihtsärgi nurgast kinni ja tema habenid ei ole mina küll mitte putnud . 
Moistmine : Ehk küll Katre Mit oma tegu salata püüab , keda tunnistaja Marjo Solnask ometi tõttes on tunnistanud . 
Otsus : Selle perast mõistis kohus Katre Mitt peab 1 rbl Jaan Säknale ja 1 rbl walla waeste ladikusse 4 nädali aea sees ära maksma . 
See otsus L . T . S § 774 ja 774 järge kohtu käijale kuulutud . 
Marjo Mitt kuulut , et tema otsusega rahul ei ole . 

</sisu>
</protokoll>
