<protokoll>
<head>
<vald>Võru murre</vald>
<aeg>xx.xx.1878</aeg>
</head>
<sisu>
Ette tulli Otto Massa ja kaibas , et Jakob Kõiw ei tahtwat temma eest pärahha massa , ni häste ei lubbawat 9 Rbl palga massa tolleperst , et temma olno ennegi leppito 3 päiwa aasta läbbi näddalilt tetta , ent Jakob Kõiw nõudwat 4 päiwa näddalist . 
Ja Tunnistaja Jakob Sikk ütles , et Otto Massa piddano ennegi üts päiw näddalist hendale sama . 
Selle päle kutsuti Jakob Kõiw kohtu ja loeti eensaiswa kaibus ette , ja utles tolleperrast ei maswat palka ei ka pärahha , et mis päiwi kiki ärra ei tenu . 
Kohtomõistus : Otto Massa peap 4 päiwa näddalist koni üts näddal päle 25 Märzi s . 
a. teenma , ent Jakob Kõiw peap tema pärahha ja 9 Rbl palka tälle masma . 
Se Kohtomõistos sai Kohtonkäüijle kulutedus , ja § 773 ja 774. 
Tal . 
säd . 
ram . 
1860. a. ärraselletedus , mis oppust andwa suremba kohtonkäümissest ja kohtonkäüja jäiwa selle mõistmissega rahhul , ja wimate sai neile ka § 881 perra se trükkito oppuse leht wälja antus . 
Päkohtomees Jürri Waldmann XXX Kohtomees Tanil Oinas XXX Kohtomees Tanil Purge XXX Kirjotaja / P.Haberland / 

</sisu>
</protokoll>
