<protokoll>
<head>
<vald>Mulgi murre</vald>
<aeg>xx.xx.1847</aeg>
</head>
<sisu>
Otsa Luiga Andresel on tüdrik Marri Toots erra surnud ja on temmal wölga naudmest Jakobij Hanso kaest 5 Rb . 
ja Jakobi sullase Peter kaest 4 Rb . 
mahha jaenut . 
Olli sies kohtomees Jaan Sorm kaesko andnut et Jakobi Hans kirsto peab teggema , sullane Peter kaewab auda ja Otsa Luiga Andres wieb tedda mahha . 
Kui agga ne möllemad mitte pölle sedda teinud , sies on Andres teinud mahha mahha matnud , ja pallob et temmale sedda waewa saab makstut . 
Jakobi Hans ütleb et see küll oige et ne 5 Rb . 
on Marri kaest woetut , on agga Marri temma poea kaest sedda waert asja warrastanud , tema poeg Jaan kes on surnud ei olle sedda wargust kohtose andnut selle perrast et ta tahtnud seda rahha wargosega tassa tahha . 
Kui agga Jaan Jakob perrast sedda erra surnud , ja temma perrandust issa kaette sanut ja see wölg ka enne sedda naisewötmest woetud sai Moistetut : Et Jakobi Hans maksab 2 Rb . 
50 kop . 
P. R. Otsa Luiga Andresse kaette ja saab Peter Paets teisel kohtopaewal seia tellitut . 
Johan Moks xxx Pea kohtomees 

</sisu>
</protokoll>
