<protokoll>
<head>
<vald>Mulgi murre</vald>
<aeg>xx.xx.1868</aeg>
</head>
<sisu>
Tulli ette Pornusse mees Hendrik Rütel ja kaebas et temma poeg Juhhan Rüitel temma Wammuse kartidega ärra mänkinud Margus orgel Eduart Kontawid ja Hans Tohwer liliga . 
Tulle ette Juhhan Rütel ja ei wöinud sallatata et ta sedda ei olle teinud ja temma annud Wammuse Hans Tohweril 4 Rubla ette panti ja Margus Orgel tulle ette ja ütles et temma ennesse Wammusse eest Hans Tohwer käest 1 Rubla lainanud ja selle ühhe rubla ollewad käiges ärra mänginud . 
Tulli ette Eduard Kondawit ja ütles et küll mänginud agga ollewad ärra leppinud selle wisiga et ta 4 Rubla Hans Tohwer ärra maksab ja Juhhan Rütel saab omma wammus taggasi . 
Otsus Juhhan Rütel saab 30 witsad , Margus Orgel 15 witsad ja Hans Tohwer jääb ommast rahhast ilma ja annab wammus taggassi . 

</sisu>
</protokoll>
