<protokoll>
<head>
<vald>idamurre</vald>
<aeg>xx.xx.1846</aeg>
</head>
<sisu>
Rannamõisas sel 23mal Aparillil 1846 aastal olliwad kokko tulnud Mõisa wallitseja ja kohtomehhed ja kõik walla peremehhed . 
1 Pea kohtomees Karel Ärdis 2 Abbi kohtomees Jaan Õja 3 Tõnno Mäggi 4 Maggasi Wöörmönder Maddis Soom 
Perremeeste nimmed . 
Rukit Odrat Kaerad 
Tunnistab Mõisa wallitsus esmesel nende perreme ? 
kümnest wõlgo 6 aastal jäinud ollewad . 
1. 
Ärdise Mihkel 
10 2 / 3 2 6 
2 Toma Mihkel 
2 3 / 4 1 1 / 2 1 
3 Reino Müwi Jakob 
4 1 / 2 1 
4 Reino Mihkel 
4 1 2 
5 Kittaski Kaarli Jürri 
4 1 1 / 2 6 
6. 
Petso Adam 
7 1 / 2 1 1 / 2 1 1 / 2 
7 Mässu Kaarli Juhhan 
4 1 1 / 2 3 
8. 
Tõntsi Josep 
6 1 1 / 2 2 
9. 
Kursi Mihkel 
6 1 6 
10. 
Pütseppa Maddis 
1 1 / 3 
11. 
Olpsi Jürri 
2 1 / 2 2 
12 Olpsi Tõnno 
2 
13. 
Enno Ado Kaarli Märt 
10 21 / 4 8 
14 Randase Karel 
1 1 / 2 2 1 / 2 
15. 
Randase Tomas 
5 2 1 / 2 5 
16. 
Randase Annus 
7 1 12 
17. 
Mäe Jaak 
3 1 6 
18. 
Mäe Tõnno 
1 / 3 2 / 3 1 1 / 3 
19. 
Mäe Peter 
2 1 2 
20. 
Leppiks Karel 
2 1 / 4 1 2 
21. 
Tosso Kaarli Jürri 
6 1 4 1 / 6 
22. 
Kergemikko Hans 
? 
2 / 3 
23 Kubja Maddis 
7 1 / 3 
24. 
Willemi Willem 
4 
25. 
Jose Tõnno 
2 2 / 3 1 3 
26. 
Andrea Märt 
2 2 / 3 1 2 1 / 2 
27. 
Seppa Karel 
2 1 4 1 / 2 
28. 
Mikko Tõnni Jürri 
4 1 / 2 
29. 
Tosso Maddis 
4 3 / 4 6 
30. 
Udde Jaan 
8 2 / 3 4 1 / 3 8 2 / 3 
31. 
Udde Mihkel 
1 1 / 3 2 / 3 1 1 / 3 
32. 
Märdi Karel 
6 
1 1 / 2 
33 Maddisse Maddis 
2 1 / 4 2 / 3 
34. 
Maddisse Mihkel 
2 2 / 3 1 / 2 1 1 / 3 
35 Lobba Jakob 
1 1 / 2 
36. 
Lobba Jaak 
2 
37. 
Lobba Kustaw 
5 1 / 2 1 
38. 
Weskimetsa Jürri 
8 
2 1 / 2 
39. 
Weskimetsa Juhhan 
2 
40. 
Reino Jakob 
1 / 2 1 / 2 1 
41. 
Reino Peter 
42. 
Waino Pedo Karel 
5 1 / 2 1 6 
43. 
Waino Pedo Jakob 
5 3 6 
44 Ado Jaan 
5 1 / 2 1 / 2 2 3 / 3 
45. 
Kreissi Märt 
7 1 1 / 2 2 2 / 3 
46. 
Waino Jaan 
8 3 9 
47. 
Pibo Maddisse Juhhan 
6 1 / 3 2 1 / 2 7 1 / 2 
48. 
Udde Annusse Jürri 
3 2 / 3 1 / 3 
49. 
Udde Jürri Juhhan 
12 4 8 
50. 
Leppa Jürri 
1 2 / 3 1 
51. 
Wenne Otto 
1 20 / 34 1 / 2 2 
52 Jurka Jaan 
1 20 / 34 1 / 2 2 
53 Wenne Tosso Jürri 
4 1 / 2 1 1 / 2 4 
54 Wenne Juhhan 
1 / 2 2 
55. 
Sorga Laar 
2 1 / 2 1 / 4 2 
56. 
Sorga Tõnno 
3 1 3 
57. 
Massuri Jaan 
1 1 / 2 
58. 
Kangro Mihkel 
4 1 / 2 1 1 / 2 6 
59. 
Tontso Hants 
3 1 / 2 1 / 2 8 1 / 3 
60. 
Janusi Jaak 
6 2 1 / 2 9 
61. 
Palloti Jago Jaan 
1 1 / 2 
62 Otto Karel 
2 2 4 1 / 2 
63. 
Reino Jürri 
4 
1 
64 Tõnno Jürri 
4 1 4 
65. 
Tõnno Juhhan 
2 1 / 2 2 
66. 
Petsi Ado 
1 1 / 3 1 1 1 / 3 
67. 
Kaiwiko Märt 
1 3 / 4 1 

</sisu>
</protokoll>
