<protokoll>
<head>
<vald>idamurre</vald>
<aeg>xx.xx.1870</aeg>
</head>
<sisu>
Jakob Pern Adrako N 16 tallo perremees sai Maggasi wõlgade pärrast Koggokonna kohto ette kutsutud ning temmale teada antud et temma Wölg rahha peale rehkendud 130 Rubla suur on ja et mis wiisi peal temma sedda tassuda tahhab . 
Jakob Pärn räkis et temmal suggugi woimalik ei olle omma wölga tassuda , ja et sellepärast Koggokonnakohhus issi tehko mis arwab tullusamb ollema . 
Moistus . 
Koggokonnakohhus annab Jakob Pärnale weel üks kuu aega ommale üht käemeest katsuda ehk issi omma tallo kellegille ärra anda , ja saab Koggokonnakohhus kerrikosambas sedda kuulutama kolm pühha , et temma asse saab oksjoni wiisil wälja pakkutud , ning sellele kes temma wöllad omma peale maksta wöttab se tallo keige Majadega ärra antud . 
Mart Jaggo XXX Mart Liis XXX Tomas Pärn XXX 

</sisu>
</protokoll>
