<protokoll>
<head>
<vald>idamurre</vald>
<aeg>xx.xx.1859</aeg>
</head>
<sisu>
Sai Mõisa poolt kaibus ette antud , et ollewa pumetsa tult teinud ösel nimmelt olnud seal jures Karel Lillo kes Tult annud Johhan Hallik ollewa se selle tulle põllema teinud Tuhha Möltri Tüdruk Lena Waida ja Ellijas Sep ollewa ka seal appist olnud . 
Sai kulatud ning olli se assi nenda õike kui een seisab mis peäle saab Mõistetud : saab Karel Lillo 10 lökika trahwitud sellepärrast et temma Laste kätte tult annud . 

</sisu>
</protokoll>
