<protokoll>
<head>
<vald>idamurre</vald>
<aeg>xx.xx.1869</aeg>
</head>
<sisu>
Sel 23mal Mai 1869 Tulli Marri Sarrap ette , ja kaebas et Jaan Abramson olla selsama talwel üks hundruk , Kedda Marri Sarrap seal jätnud , ja mis Jaan Abramsoni Naene olla moisas wiinud ning pantis pandnud . 
Kui ka üks Rubla rahha mis 7 aasta eest antud ja taggasi ei pea makstama . 
Sai Jaan Abramson ette Kutsutud . 
Kes ütles , et ta sellepärrast undruk pantiks walinud , miks Maie Sarrap temma võlglane peab ollema . 
Kedda Jaan Abramson ei võenud õigest tehha . 
Moistis Kohhos selle peale , et Jaan Abramson peab Marri Sarrapu undruk tullewal Reedel Kätte tooma . 
Kui mitte siis maksap Jaan Abramson Tüdrike jalla vaewa . 
Tõnnis Soiewa + + + Karel Rosenberg + + + Jürri Priks + + + 

</sisu>
</protokoll>
