<protokoll>
<head>
<vald>idamurre</vald>
<aeg>xx.xx.1864</aeg>
</head>
<sisu>
Kohto mees Mart Niggul XXX Kohto mees Jaan Täht XXX Kohto mees Juhan Karro XXX Wöörmünder Mart Kuk XXX Juhhan KütKurrema walla mees tulli ette , ja kaebas et Jakop Täht temma hobbost te pealt tulnud käest ärra wõtma , ja kui temma hobbost mitte annud . 
siis Jakop Täht tedda kolm korda aja teibaga on lönud . 
Jakop Täht wastas selle peale , et temma selle pärrast on hobbost tahtnud kinni wõtta , et Juhhan Küt ülle kõrre wälja on sõitnud ja tedda kolm korda lönud . 
Tunnismees Mart Wilk tunnistab temma on kuulnud et kolm löki on lödud , agga temma mitte näinud , keddas lödud . 
Moistus : Koggokonna kohhus mõistis et Jakop Täht 25 witsa löki peab sama selle eest , et temma üht tee käiad lähheb röwima , kui sealt on lubbatud käia . 
C Friedrich Mandel [ allkiri ] 

</sisu>
</protokoll>
