<protokoll>
<head>
<vald>saarte murre</vald>
<aeg>xx.xx.1895</aeg>
</head>
<sisu>
Emmaste walla talunikud Andrus Haldrik , Juhan Lund ja Juhannes Põld , kes kohtule tuntud , palusiwad nendelt sisse antud kirjaliku lepingut selle kohtu raamatusse kirjutada : Laewa " Maria-Amalia " kiper Andrus Haldrik , kauples 1895a . meresõiduajaks , mis temal 22skp Haapsalu linna sadamas algab , laewa peale madrusteks , Juhan Lund üheksa rubla 50kopika kuu palgaga ja Juhannes Põld kaheksa rubla kuupalgaga . 
- See leping sai pärast lepingu raamatusse kirjutamist pooltele ette loetud ja nendelt alla kirjutatud . 
- Ustawaks tunnitatud lepingu wõttis wasta P. Haldrik 

</sisu>
</protokoll>
