<protokoll>
<head>
<vald>saarte murre</vald>
<aeg>xx.xx.1896</aeg>
</head>
<sisu>
Ükstuhat kaheksasada üheksakümmend kuuendamal aastal Jüri kuu wiiendamal päewal , Emmaste wallast kiper Johannes Wäljas , talumehed Priidu Tänawa ja Peeter Haldrik , kes kohtule tuntud , palusiwad nendelt sisseantud kirjaliku lepingut selle kohtu lepingu raamatusse üles wötta : Laewa " Salme " kiper Johannes Wäljas kauples tänawuse mere söidu ajaks , mis kuuetäistkümnemal selle kuupäewal Puulaidus algab , laewapeale madrusteks Priidu Tänawa ja Peeter Haldrik kumbgi kaheteistkümne rubla kuupalgaga . 
See leping sai pärast lepinguraamatusse kirjutamist pooltele ette loetud , Juhannes Wäljaselt , Priidu Tänawalt , aga Peeter Haldrik palwe peale , kes ise kirja ei oska , Andrus Haldrikult alla kirjutatud , mis kohus õigeks tunnistab . 
- Ustawaks tunnistatud lepingu wõttis wasta J. Wäljas 

</sisu>
</protokoll>
