<protokoll>
<head>
<vald>saarte murre</vald>
<aeg>xx.xx.1884</aeg>
</head>
<sisu>
Sellega tunnistawad Juhan Kerner ja Andrus Kersen et need majad , mis Andrus Kersen Juhan Kerneri käest ostnud nüüd wälja kõik makstud on see on 120 rubla ( üks sada kaks km ) . 
Juhan Kerner lubab et tema ei tule küll enne kolme aastad tagasi talu kohast . 
On aga see et Juhan Kerner kas ära sureb , siis wõiwad tema lapsed seda maja enne kolme aastad pärida , kui selle maja hinna tagasi makswad . 
Pärast kolme aastad jäeb aga maja täielikuks Andrus Kerseni omanduseks . 
Talitaja M.Kebuse , Kirjutaja Th . 
Piik 

</sisu>
</protokoll>
