<protokoll>
<head>
<vald>saarte murre</vald>
<aeg>xx.xx.1875</aeg>
</head>
<sisu>
Tennasel päwal tunnistas Peter Lahtein omma haige wodi peäl , mis taal ühhegi käest sada on . 
Haustlu Kokki Norri ligi käest Norri eest 5 Rubla üks warbi kois 20 sülda eest 5 Rubla masti tallid 1 Rub 20 k Linnast ostand wappi 1 Rubla 50 kop Ankru ketted 3 Rubla Sum 15 Rub 90 kop Attlast Endrika Mihkli käes 70 kop Mihkel on ta käest 7 N : wörgo sallist wöttand Allika Ado 6 N wörgo sellist 60 kop Lause Jaen 2 Rubla raua eest Kuusnömm Reino Redika käest 60 kop Seppaste Kaarli käest 70 kop Taggamoisast Lennarti Jürna käest 1 Ro 40 kop Meedri Simmo kää on 6 räime wörko löötso keige seppa riistadega 20 kakskümmend wakka ruggi wilja 30 wakka kartuhlid hobbune lehm 2 sigga uhhe hobbuse raud rattad wannad paari ellajate raud rattad arwatud 8 Rubla Lause Jaen maksab Simmule sedda raua rahha künla kuu 1ks päwaks 1 Rub ärra 1876 ja 1 Rubla küünla kuu 1ks 1877. 
2 Rubla ärra maksetud . 
Pea kohto mees Ado Tarkin Tallitaja Jaak Talp 

</sisu>
</protokoll>
