<protokoll>
<head>
<vald>saarte murre</vald>
<aeg>xx.xx.1895</aeg>
</head>
<sisu>
1895a . 
, Küinla k . 
3. päewal , Emmaste walla talunik Peeter Lige , kes kohtule tuntud , palus omalt üles antud suusöna ülesandmist kohtu kirja üles wötta : Priidu Lige'le luban mina wölgu olewat kuuskümmend kuus rubla ( 66 rubla ) 15. 
Aprilliks 1895a . ära tasuda ; looma pöhust ja toidu kraamist , mis 1894 aastal saadud , wilja seemet maha arwates , luban Priidule ühe kolmandiku osa ja peale see korterit kuni Mihkli päewani 1895 aasta . 
- ( " kuus " öige ) Et Peeter Lige ise kirja ei oska , siis kirjutas tema palwe peale alla M. Remmelg . 
M. Remmelg kirjutas Peeter Lige eest alla , sest et wiimane kirja ei oska . 
Wanem : J. Söel . 
Kirjutaja : Brever . 

</sisu>
</protokoll>
