<protokoll>
<head>
<vald>Tartu murre</vald>
<aeg>xx.xx.1885</aeg>
</head>
<sisu>
Hindrik Petersoni kaebduses wastu Hans Normann tööpalga nõudmise pärast , protokoll Nr 121 , ütel tunnistaja Jaan Aloel , Anne mõisast . 
Tema ütles küsimise pääle , et 3. Oktoobril 1884 aastal maksnud Hans Normann Hindrik Petersonile 5 Rubla töö palka kätte . 
Pääle Nuustaku laada mitte enam sinna töösse tulnud . 
Tunnistaja Peeter Sonne , Ilmjärwest , puudub . 
Otsus : Tunnistaja Peeter Sonne Ilmjärwest wahi all ette kutsuda . 

</sisu>
</protokoll>
