<protokoll>
<head>
<vald>Tartu murre</vald>
<aeg>xx.xx.1882</aeg>
</head>
<sisu>
Tuli ette Liis Iwanthal ja kaebas Adam Mülleri man saisten : Josep Jürgenson on temaga lihalikkult elanud , mispääle temal Mai kuu sees s . 
a. poig olnud , ning nöudis 100 rubl . 
lapse üleskaswatamiseks . 
Josep Jürgenson kaebtuse üle küsitud , salgab kaibajaga lihalikult elanud olewat . 
Liis Iwanthal wastutas selle pääle : kui tema Wönno oppetaja herra man Josep Jürgensoni paari kuulutust ära on keelnud ja oppetaja teda mitte laulatada ei ole tahtnud , siis on Jürgenson seda oppetajale ära tunnistanud . 
Josep Jürgenson ütles : tema ei ole oppetajale midagi tunnistanud . 
Möistus : Josep Jürgenson peab iga aasta 10 rubl . 
Liis Iwanthali hääks lapse ülespidamiseks maksma , kuni laps 10 aastad wanaks saab . 
Peter Kripson XXX Peter Hendrikson XXX Hendrik Piirson XXX Kotta Wossmann XXX 
Möistus sai kohtukäijatele T . S . R . pärra a. 1860 § 772 - 774 kuulutud ja öppus antud , mis tähele tuleb panna , kui keegi körgemat kohut tahab käija ja ei olnud Josep Jürgenson mitte sellega rahul . 

</sisu>
</protokoll>
