<protokoll>
<head>
<vald>Tartu murre</vald>
<aeg>xx.xx.1884</aeg>
</head>
<sisu>
Ahja mõisa metsa walitsus kaebas et Liis Tilba mõisa metsast oma tare ehitamiseks 8 pedajad warastanud . 
Need palgid olnud metsas ära märgitud - nõuab 24 rubl . 
Liis Tilba wastutas selle peale et tema ühe ainsa Ahja mõtsast on toonud muido on tema köik Kroonu mõtsast toonud . 
Metsawaht Jakob Hindrikson tunnistas et ülesantud kaebtus õige on . 
Kohtumees Kota Wossmann kes neid palke ülekaenud , andis protokolli et tema Liis Tilba tare seinas 6 märgitud palki leidnud . 
Mõiste : Liis Tilba peab 3 rubl . 
8 päiwa sees metsa walitsuse hääks wälja maksma . 
Peakohtumees : P. Kripson XXX Kohtumees : P. Hindrikson XXX Kohtumees : K. Wossmann XXX Kohtumees : K. Iwanthal XXX 
Mõiste sai kohtukäijatele T . S . R . pärra a. 1860 § 772 - 774 kuulutatud ja ei olnud metsa walitus sellega rahul . 
Kirjutaja : Ch Kapp <allkiri> 

</sisu>
</protokoll>
