<protokoll>
<head>
<vald>Tartu murre</vald>
<aeg>xx.xx.1885</aeg>
</head>
<sisu>
Ado Raudsep Wanna Koigolast Kaebas , et temal Johan Tälli käest 250 rubl . 
ja selle protsenti 39 rubl . 
saada on , nõuab seda kätte . 
Johan Tälli wastutas selle pääle , et temal ainult 150 rubl . 
ja selle aasta 2 aasta protsent 18 rubl . 
maksa on . 
Moiste : Johan Täll peab üle kõige 168 rubl . 
8 päewa sees Ado Raudsepa hääks wälja maksma . 
Peakohtomees : P. Kripson XXX Kohtomees : P. Hindrikson XXX Kohtomees : K Wossmann XXX Kohtomees : J Klaosoon 
Moiste sai kohtokäijatele T . S . R . pärra a. 1860 § 772 - 774 kuulutud ja õpus antud mis tähele tulep panna kõrgema kohto käimises ning ei olnud Adam Raudsep mitte sellega rahul . 
Kirjutaja : Ch Kapp <allkiri> 
5 Febr 1885 Kihelk kohto sisse saadetud 

</sisu>
</protokoll>
