<protokoll>
<head>
<vald>Tartu murre</vald>
<aeg>xx.xx.1886</aeg>
</head>
<sisu>
Peeter Zubas kaibas , et temal Jakop Hindriksoni käest 1 1 / 2 rbl . 
lina ajamise mashina pruukimise eest saa on - nõuab kätte . 
Jakop Hindrikson ei salga ütleb aga et linaluud sinna jäänud . 
Mõiste : Jakop Hindrikson maksab Peeter Zubassele 8 päiwa sees 1 rbl . 
linamasina pruukimise eest wälja ja ei wastastiku nõudmist enam . 
Pääkohtumees : P. Kripson XXX Kohtumees : Jaan Ottan XXX Kohtumees : P. Pedoson XXX Kohtumees : Johan Kiljak <allkiri> Kohtumees : Kotta Piir <allkiri> 
Mõiste sai kohtukäijatele kuulutatud . 
Kirjutaja : 

</sisu>
</protokoll>
