<protokoll>
<head>
<vald>Tartu murre</vald>
<aeg>xx.xx.1886</aeg>
</head>
<sisu>
Jaan Tennokene kaibas et Peeter Joonas teda terwe minewa suwi pidanud teenima 60 rbl . 
eest ; aga 60 päiwa on tema teeninud ja selle pääle 24 rubla wõtnud ; päält see on ta weel 12 rubla eest jahu ette wõtnud - nõuab et ta selle puuduwa aja järgi teenib ehk kaubeldut aasta palga tasumiseks maksab . 
Peeter Joonas wastutas et tema kuude wiisi kauba teinud ; kuu eest 12 rubla - ja on tema 3 kuud ära teeninud mille järele tema midagi ette ei ole wõtnud . 
Jaan Teral tunnistas , et kaup arwata nõndasama kui temalgi suwe pääle on tehtud . 
Jüri Hein tunnistas , et kaup suwe pääle tehtud ja on 12 rbl . 
kuu see on suwe eest 60 rubla kaubeldud ; kas Joonas palka ette on saanud , ei tea tema . 
Mõiste : Peeter Joonas peab puudus jäänud 65 päiwa Jaan Tennokese juures ära teenima ja saab siis weel , et ta 36 rubla kätte saanud , 24 rubla palka ehk maksab wastalisel korral Jaan Tennokesele , et enne kaubeldut aiga ära on läinud , täis suwe palk 60 rbl . 
tagasi . 
Kohtumees : Jaan Ottan 
Säädusliku mõiste kuulutuse juures lubas Peeter Joonas teenima minna . 
Kirjutaja : Chr Kapp <allkiri> 

</sisu>
</protokoll>
