<protokoll>
<head>
<vald>Tartu murre</vald>
<aeg>xx.xx.1886</aeg>
</head>
<sisu>
Kusta Must kaebas , et temal oma peremehe Jaan Piiri käest wana palka 15 rbla saada ja kolm hobuse päewa saada , mis tema kätte nõuab . 
Jaan Piir wastutas , et tema Jüripäew palga poisiga ära seletanud ja jäänud 15 rbla selle ette , et poiss ühe uuri ära wõtnud . 
Mõiste : Et Jüripäew palk seletatud saanud , siis ei wõi Kusta Must midagi Jaan Piiri käest nõuda . 
Mõiste sai kohtu käijatele kuulutud . 

</sisu>
</protokoll>
