<protokoll>
<head>
<vald>Tartu murre</vald>
<aeg>xx.xx.1886</aeg>
</head>
<sisu>
Jüri Herzmann kaebas , et tema naine Sulbi weski juurde 40 küünard willast rõiwast wanutama wiinud , aga tambi alt on rõiwas ära kadunud ja nõuab mölder Karl Parwei käest 40 rbla kahjutasumist . 
Mölder Karl Parwei ütles kaebtuse peale , Jüri Hertzmani naine pidanud ise wanutamise tambi juures olema , nõnda kui kõik töisedki wanutajad ; aga tema olewat juurest ära läinud ilma tääda andmata , siis ei wõi see mitte tema süü alla , kui rõiwas kadunud , waid peab Jüri Hertzmani naine seda wastutama . 
Enne wanutamist on tema ( Karl Parwei ) rõiwa ära möötnud ja olnud seda 40 küünart . 
Mõiste : Mölder Karl Parwei peab 70 kop . 
iga küünra eest see teeb 28 rbla Jüri Hertzmani hääks 8 päewa sees wälja maksma . 
Mõiste sai kohtukäijatele T . S . R . järele a. 1860 § 772 - 774 kuulutud ja ei olnud kohtukäijad sellega rahul . 

</sisu>
</protokoll>
