<protokoll>
<head>
<vald>Tartu murre</vald>
<aeg>xx.xx.1886</aeg>
</head>
<sisu>
Jakob Hindrikson kaebas , et Johan Mägi temale nelja wakka maa renti 20 rbla wõlgu , mis tema kätte nõuab . 
Johan Mägi wastutas , et temal 2 wakkamaad 6 rbla eest ja 1 wakka maa poole toobi wiina eest Jakob Hindriksoni käest rentinud . 
Kohtumees Jaan Ottan tunnistas : Tema kuulnud , et 3 wakkamaad rentitud olnud ja pidanud Mägi 3 rbla wakkamaa eest maksma . 
Mõiste : Johan Mägi peab 8 päewa sees 9 rbla renditud maa eest Jakob Hindriksonile wälja maksma . 
Mõiste sai kohtukäijatele kuulutatud . 
Peakohtumees : P. Kripson XXX Kohtumees : P. Peedosson XXX Kohtumees : Jaan Ottan XXX 
Kirjutaja : Chr Kapp <allkiri> 

</sisu>
</protokoll>
