<protokoll>
<head>
<vald>Tartu murre</vald>
<aeg>xx.xx.1888</aeg>
</head>
<sisu>
Kusta Matsin kaibas , et Mihkel Soe hobused tema keswa ära on söönud ning on tema hobused kinni wõtnud , Mihkel Soe on aga sulase käest hobuse ärawõtnud - nõuab 3 rbl . 
Mihkel Soe wastutas , et tema hobused mitte kaibaja keswas olnud ei ole ; tema olla aga kaibaja hobused enda koplist kinniajanud . 
Kohtumees J. Rootslane andis protokolli , et kaebatawa wend Jaan Soe ja selle sõsar temale üttelnud on et nende hobune küll Kusta Matsini keswas olnud . 
Mõiste : Mihkel Soe maksab 1 rbl . 
Kusta Matsinile 8 päewa sees , hobuse kinni wõtmise eest wälja . 
Mõiste sai kohtukäijatele kulutatud T . S . R . järele a. 1860 § 772 - 774 järele ning ollid kohtukäijad rahu . 
Pääkohtumees : Peeter Kripson Kohtumees : Jaan Ottan Kohtumees : P. Pedosoon 
Kirjutaja asem . 
M. Rosentaal <allkiri> 

</sisu>
</protokoll>
