<protokoll>
<head>
<vald>Tartu murre</vald>
<aeg>xx.xx.1888</aeg>
</head>
<sisu>
Jakob Hindrikson kaebas , et allpool tähendatud peremeeste lammad tema keswad ära tallanud ja söönud ning nimelt : 
Jaan Kurel 2 õhwakest 
Jüri Wallil 4 lammast 
Kusta Molokal 5 lammast 
Madis Lattil 6 lammast 
Tema nõuab keswa põllu eest 15 rbl . 
ja Jaan Kure käest 10 rbl . 
kaera söötmise kahju . 
Jaan Kure salgab . 
Jüri Wall ütleb , et üks lammas kinni olnud wõetud . 
Kusta Molok ei tea midagi . 
Madis Lätti ei ole tulnud . 
Kaebatawad ütlewad , et tema enda elajad wilja ära söötnud . 
Walla wöörmönder Jaan Hansing andis üles , et Kaara kahju 1 rbl . 
ja keswa kahju 2 rbl . 
wäärt on . 
Mõiste : Jaan Kure maksab 1 rbl . 
Jüri Wall 50 Kop . 
Kusta Molok 50 Kop . 
ja Madis Lätti 1 rbl . 
Jakob Hindriksoni hääks 8 pääwa sees Kahjutasumist . 
Mõiste sai Kohtukäijatele T . S . R järel a. 1860 § 772 - 774 kuulutud ja et Hindrikson rahul ei olnud , õpusleht wälja antud . 

</sisu>
</protokoll>
