<protokoll>
<head>
<vald>Tartu murre</vald>
<aeg>xx.xx.1868</aeg>
</head>
<sisu>
Sell sammal päiwal kaibas kah Nekrut Johan Põdder , et Lowisa Hintzer on temmal 10 Rubl . 
hõb . 
Wõlgu ja ei maksa mitte ärra , kelle perrast temma kohhut pallel sedda rahha temmale kätte awwitada murretsema ja andis kah weel Johan Luhhad , kes sest Assjast tiab , Tunnistusest ülles . 
Luwisa Hintzer es olle mitte sia Kohto Kutsmisse perra tulnu , wait enneki Tunnistaja Johan Luhha , se küssitud , wastotas : et temma sest Assjast mitte middagi ei tia . 
Ahjawallawannemb Jaak Koor , kes just siin olli , asSe ülles , ja ütles : et ni kui temma sest Kaibussest kah on teada sanu , on temma Lowisa Hintzeriga selle perrast kõnnelnu , ent om kah se üttelnu , et temma sest rahhast mitte middagi ei tia . 
Sai moistetud : Johan Põdder otsigu parrembad Tunnistust omma Kaibusse Assjale . 
Se Moistminne sai kulutud . 
Peter Issakson XXX Josep Adoson XXX Peter Akkert XXX Johan Laan XXX 

</sisu>
</protokoll>
