<protokoll>
<head>
<vald>Tartu murre</vald>
<aeg>xx.xx.1869</aeg>
</head>
<sisu>
Sell sammal päiwal tulli ette Leno Peter Parksepa naine kaibas tolle ülle , et se Mai Parksep , kes temma Mehhe Issa töine Naine om , om tedda häbbematta wiisil sõimanu ja omma wanna Meest ilma röiwida tarrast lumme päle wälja wissanu . 
Mai Parksep ettekutsutud : nimmetas kah siin Kohto een omma woera poia Naist Hooras ja ütles , et temma om neide kiige töitja ja kostja , laitis Oppetaja Herrad , et kah se ei anna temmale Oigust otsekui Koggokonna kohhus , ja olli ka siis mudi krob . 
Sai moistetud : Mai Parksep 3 päiwast Wahhi alla Turmi panda 
Se Moistminne sai kulutud etc . 
etc . 
etc . 
ja Mai Turmi pantud . 
Peter Issakson XXX Josep Adoson XXX Johan Laan XXX Peter Akkert XXX Widrik Harkmann XXX 

</sisu>
</protokoll>
