<protokoll>
<head>
<vald>Tartu murre</vald>
<aeg>xx.xx.1871</aeg>
</head>
<sisu>
Tämba tulli ette Kotta Piirson ja andis ülles , et temma tahhab töise Abbi Ello sisse astu se Kurrista Walla tütrikuga Liis Schumann , Jaan Jostow tütter , ja lubbas ommile lapsile eddimetse Abbiellust , ni kui : 
1. poeg Jaan 
Tarre - Kondra Maa pääl 
2. poeg Indrik 
1 lammas ja üts hõbbe Selg 
3. poeg Peter 
1 lammas - üts kask 
4. poeg Daniel 
1 Zigga - üts ImmaKirst 
5. tütter Marri 
lehm ja 2 willast Undriko 
Sedda tunnistawad Kotta Piirson XXX Jakob Naggel XXX Peter Laar XXX Hindrik Sikkut XXX 

</sisu>
</protokoll>
