<protokoll>
<head>
<vald>Tartu murre</vald>
<aeg>xx.xx.1885</aeg>
</head>
<sisu>
Tuli ette Ahja walla liige Hendrik Molok ja palus protokolli üles wõtta : tema wõtab Mäksa walla liikme Peeter Niluse poja Juhan Niluse , sündinud Detsembri kuul 1878 , Liiwimaa T . S . R . põhjuse peale a. 1860 § 952 omale poja asemele , sest et temal endal abielus poeg lapsi ei ole , kõige õiguste ja kohustega , mis ihulikul lapsel on , kellega ka Peeter Nilus rahul oli . 
Seda tunnistawad nemad oma allkirjaga Hintrig Mollog <allkiri> Peter Nilus XXX Otsus : Seda protokolli ülespanna 
Peakohtumees : Peeter Kripson XXX Kohtumees : Peeter Hindrikson XXX Kohtumees : Jaan Hansing <allkiri> Kirjutaja : Chr Kapp <allkiri> 

</sisu>
</protokoll>
