<protokoll>
<head>
<vald>Tartu murre</vald>
<aeg>xx.xx.1894</aeg>
</head>
<sisu>
Tulid Ette : Ahjamõisa omaniku A von Braschi woliwõtja , metsawalitseja Eugen Adamson , ja Antonius Tätte ja andis esimene nende wahel tehtud ning sell samal , ülemal nimetatud päewal No 29 all kinnitatud kontrahti täientuseks üles : 1. 
Antonius Tätte wõttab kontrahtiga küll Singa metsawahi koha praeguses olekus , kus nurmed kündmata ning rukkit wähem külwatud kui kontraht nõuab wana metsawahi käest wastu aga käest ära andmisel peab kõik põllu ja majapidamine just nii olema nagu sell päewal 28 Oktobr . 
1894 a. tehtud leppingus ( kontrahtis ) maha tehtud 2. 
Ei wõi Antonius Tätte midagi selle eest kahjutasumist nõuuda , kui wast wana metsawaht ei peaks ilma kohtuta omast kohast õigel ajal wäljaminema ning selleläbi Tättele mõnda takkistust kas korteri ehk muu poolest tegema . 
3. 
Saab Tätte selle eest et juba küünlapäewal 1895 a. peale ametisse astub seni kui päris kontrahti alguni s.o. Jüripäewani 1895a neli wakka rükkid mis mitte kontrahtis nimetatud pole E Adamson <allkiri> Antonius Tätte <allkiri> 
Et kohus wastasid pooli tunneb ja et nad oma käega on allakirjutanud saab sellega tunnistatud . 
Eesistuja J. Kooskord Kirjutaja : Puusepp 

</sisu>
</protokoll>
