<protokoll>
<head>
<vald>Tartu murre</vald>
<aeg>xx.xx.1866</aeg>
</head>
<sisu>
Tuli ette Johan Kahho nink Surel Redie tulli minna Kassi Körtsi mäe pääl nink olle minnol üts wijul silu al , sääl tulle minnole Kidjerwe Anne Sare tallo sullane Peter Leib nink Rise se Wijol minno Käest ärra . 
sele ülle om Johan Rihm tunnistaija . 
saije ette kutsutus Johan Rihm nink kussitus kas Peter Leib wötse waggisi Poisikesse Johan Kahho kaest , wotse Kül Kostse Johan Rihm , sai ette Kutsutud Peter Leib , nink Peter Leib es wabbanda et ta Poisikesse Johan Kahho käest Wijul om Risnu . 
Kohhus Moistis Et Peter Leib massap Waeste Ladikkehhe Kats Rbl . 
Trahwi nink se poisile et Peter Leib minnewä Kohto päiwal Kohto ette ei tulle nink pois Kats Körd Kohtohhe piddi tullema nellikummend koppikut poisile aija witmisse eest . 
Pä Kohtomees : Peter Tarrask <allkiri> Kohtumees Jaan Peetsu XXX Abbi Jaan Petso XXX Abbi Johan Lük XXX Abbi Johan Wisk XXX 

</sisu>
</protokoll>
