<protokoll>
<head>
<vald>Tartu murre</vald>
<aeg>xx.xx.1890</aeg>
</head>
<sisu>
Tiidu Peeter Luts astus ette ja palus protokolli kirjutada , et ta on surnud Märt Lutsu venna Jaak Lutsule tema pääle maksa jäänud raha 15rbl . 
ja järgi jäänud kraami kätte annud , mida Jaak Luts ka vastavõtnud , mis ta ise ka siin tõeks on tunnistanud . 
eioska oma nime kirjutada . 
Otsus : Protokolli kirjutada . 
Pääkohtumees M Roth ( allkiri ) Kohtumees J Järlof ( allkiri ) Kohtumees P Lewertand ( allkiri ) Kohtumees H Kangur ( allkiri ) Kirjut ( allkiri ) 

</sisu>
</protokoll>
