<protokoll>
<head>
<vald>Tartu murre</vald>
<aeg>xx.xx.1871</aeg>
</head>
<sisu>
Sell sammal päiwäl tulli ette Peter Zakkarjas , Pedaspält ja andes ülles , et temma ei woi ennamb sedda Maja piddada ja tahhab sedda käest anda , seda et temma Wennemale ellama lähhab PornaKantori alla . 
Temmaga üttehopid talli sia Jaak Ilpus jän pallel seada Maja hinda katte wõtha ni kui temma praego om ja lubbab kiige est ni kui toise vistest , wastata Sedda wokki kaalda ja lubbate sedda tehha . 
Tunnistassest : Peter Zakkarajas XXX Jaak Ilpus 

</sisu>
</protokoll>
