<protokoll>
<head>
<vald>Tartu murre</vald>
<aeg>xx.xx.1827</aeg>
</head>
<sisu>
Sel 27mal Aprilli 1827. 
Koggokonna Pä Kohtomees Jakob Tolmaz olli man . 
Moisa wallitseja ningk Peter Reitdorff teggi se Leppingk : et Peter wottop Retzniko Majawahhi Ammeti , ningk om se Kaup nenda tettut , ütte Aasta päle . 
1 , et temma saap sest tallomast igga Nurmes 1 Teomaa enda jaust , ningk pool need Tallo Aijamaad . 
2 , Temma orjap nende maade est moisale pole Talwe Linnasepappi Ammeti , truuste ningk öige , ningk kui johhus temma üts Petminne teggema , siis pannakse temma sedda tasuma , ningk saap temma sest Ammetist walla . 
3 , Temma wahhip omma Tallo Mötsa perra , ningk wöttap Warga kinni ja toop Moisale trawwida . 
4 , Moisa ei sunni temma Nietmisse ning Poimamisse man , mis Moisa jaust om . 
5 , Temmale antakse Allamäs se Ainamaa enda jaust . 
6 , Temma wottap Ingemaast 3rbl . 
30kop . 
ningk Kihhelkonnakohto = ja walla Kohtomeeste palk massa seetut ajal tallitada . 
Parrandap Posti = ningk ka Kirriko Teed ; ningk parrandab Tallo kattuset . 
7 , Muud Orjusest om temma walla . 
Peter Reitdoff XXX Jakob Tolmatz XXX G L Kreijtenberg ( mõisavalitseja allkiri ) 

</sisu>
</protokoll>
